audb/__init__.py
audb/core/__init__.py
audb/core/api.py
audb/core/cache.py
audb/core/config.py
audb/core/conftest.py
audb/core/define.py
audb/core/dependencies.py
audb/core/flavor.py
audb/core/info.py
audb/core/load.py
audb/core/load_to.py
audb/core/lock.py
audb/core/publish.py
audb/core/repository.py
audb/core/stream.py
audb/core/utils.py
audb/core/etc/audb.yaml
audb/info/__init__.py
benchmarks/README.md
benchmarks/benchmark-dependencies-methods-polars.py
benchmarks/benchmark-dependencies-methods.py
benchmarks/benchmark-dependencies-save-and-load.py
benchmarks/compare_dependency_methods_polars.py
benchmarks/dependencies_polars.py
benchmarks/requirements.txt
docs/authentication.rst
docs/caching.rst
docs/changelog.rst
docs/conf.py
docs/configuration.rst
docs/conftest.py
docs/contributing.rst
docs/dependencies.rst
docs/genindex.rst
docs/index.rst
docs/install.rst
docs/load.rst
docs/overview.rst
docs/publish.rst
docs/quickstart.rst
docs/requirements.txt
docs/_templates/autosummary/class.rst
docs/api-src/audb.info.rst
docs/api-src/audb.rst
docs/pics/load.dot
docs/pics/publish.dot
tests/conftest.py
tests/requirements.txt
tests/test_api.py
tests/test_attachments.py
tests/test_backend.py
tests/test_cache.py
tests/test_config.py
tests/test_convert.py
tests/test_dependencies.py
tests/test_filter.py
tests/test_flavor.py
tests/test_info.py
tests/test_load.py
tests/test_load_on_demand.py
tests/test_lock.py
tests/test_lock_db.py
tests/test_publish.py
tests/test_publish_table.py
tests/test_remove.py
tests/test_repository.py
tests/test_stream.py
tests/assests/dependency-table-pandas/.gitignore
tests/assests/dependency-table-pandas/README.md
tests/assests/dependency-table-pandas/emodb-pandas-2.0.3.pkl
tests/assests/dependency-table-pandas/emodb-pandas-2.1.4.pkl
tests/assests/dependency-table-pandas/emodb-pandas-2.2.2.pkl
tests/assests/dependency-table-pandas/store_dependency_table.py
tests/assests/dependency-table-pandas/store_dependency_tables.sh
audb-1.11.3.dist-info/LICENSE
audb-1.11.3.dist-info/METADATA
audb-1.11.3.dist-info/WHEEL
audb-1.11.3.dist-info/top_level.txt
audb-1.11.3.dist-info/RECORD
