Metadata-Version: 2.2
Name: audb
Version: 1.11.3
Summary: Load and publish databases in audformat
Author: Johannes Wagner
Author-email: Hagen Wierstorf <hwierstorf@audeering.com>, Christian Geng <cgeng@audeering.com>
License: MIT License
Project-URL: repository, https://github.com/audeering/audb/
Project-URL: documentation, https://audeering.github.io/audb/
Keywords: audio,data,dataset,annotation,mlops,machine learning
Classifier: Development Status :: 5 - Production/Stable
Classifier: Intended Audience :: Science/Research
Classifier: Intended Audience :: Developers
Classifier: License :: OSI Approved :: MIT License
Classifier: Operating System :: OS Independent
Classifier: Programming Language :: Python
Classifier: Programming Language :: Python :: 3
Classifier: Programming Language :: Python :: 3.9
Classifier: Programming Language :: Python :: 3.10
Classifier: Programming Language :: Python :: 3.11
Classifier: Programming Language :: Python :: 3.12
Classifier: Programming Language :: Python :: 3.13
Classifier: Topic :: Scientific/Engineering
Requires-Python: >=3.9
License-File: LICENSE
Requires-Dist: audbackend[all]>=2.2.2
Requires-Dist: audeer>=2.2.0
Requires-Dist: audformat>=1.2.0
Requires-Dist: audiofile>=1.0.0
Requires-Dist: audobject>=0.5.0
Requires-Dist: audresample>=0.1.6
Requires-Dist: filelock
Requires-Dist: oyaml
Requires-Dist: pandas>=2.1.0
Requires-Dist: pyarrow
